ariadne_extended/__init__.py
ariadne_extended/contrib/waffle_graph/__init__py
ariadne_extended/contrib/waffle_graph/app.py
ariadne_extended/contrib/waffle_graph/resolvers.py
ariadne_extended/contrib/waffle_graph/schema.graphql
ariadne_extended/contrib/waffle_graph/types.py
ariadne_extended/cursor_pagination/__init__.py
ariadne_extended/cursor_pagination/mixins.py
ariadne_extended/cursor_pagination/pagination.py
ariadne_extended/cursor_pagination/resolvers.py
ariadne_extended/cursor_pagination/schema.graphql
ariadne_extended/cursor_pagination/types.py
ariadne_extended/filters/__init__.py
ariadne_extended/filters/backends.py
ariadne_extended/filters/mixins.py
ariadne_extended/graph_loader/__init__.py
ariadne_extended/graph_loader/apps.py
ariadne_extended/payload/resolvers.py
ariadne_extended/payload/schema.graphql
ariadne_extended/payload/types.py
ariadne_extended/permissions.py
ariadne_extended/resolvers/__init__.py
ariadne_extended/resolvers/abc.py
ariadne_extended/resolvers/exceptions.py
ariadne_extended/resolvers/mixins.py
ariadne_extended/resolvers/model.py
ariadne_extended/settings.py
ariadne_extended/utils/abc.py
ariadne_extended/utils/monkey.py
ariadne_extended/uuid/__init__.py
ariadne_extended/uuid/schema.graphql
ariadne_extended/uuid/types.py
ariadne_extended/views.py
ariadne_extended-0.2.5.dist-info/LICENSE.md
ariadne_extended-0.2.5.dist-info/WHEEL
ariadne_extended-0.2.5.dist-info/METADATA
ariadne_extended-0.2.5.dist-info/RECORD
