Metadata-Version: 2.1
Name: ariadne-extended
Version: 0.2.5
Summary: Ariadne contrib library for working with Django and GraphQL
Home-page: https://github.com/patriotresearch/ariadne-extended
License: MIT
Keywords: ariadne-extended
Author: Patrick Forringer
Author-email: pforringer@patriotrc.com
Requires-Python: >=3.7,<4.0
Classifier: Development Status :: 2 - Pre-Alpha
Classifier: Framework :: Django
Classifier: Intended Audience :: Developers
Classifier: License :: OSI Approved :: MIT License
Classifier: Natural Language :: English
Classifier: Programming Language :: Python
Classifier: Programming Language :: Python :: 3
Classifier: Programming Language :: Python :: 3.7
Classifier: Programming Language :: Python :: 3.8
Classifier: Programming Language :: Python :: 3.9
Classifier: Programming Language :: Python :: Implementation :: CPython
Classifier: Programming Language :: Python :: Implementation :: PyPy
Classifier: Topic :: Software Development
Requires-Dist: ariadne (>=0.13.0,<0.14.0)
Requires-Dist: django (>=2.2,<=3.3)
Requires-Dist: django-filter (>=2,<3)
Requires-Dist: django-waffle (>=0,<2.1)
Requires-Dist: djangorestframework (>=3.7,<4.0)
Requires-Dist: pyhumps (>=1.6.1,<2.0.0)
Project-URL: Bug Tracker, https://github.com/patriotresearch/ariadne-extended/issues
Project-URL: Documentation, https://ariadne-extended.readthedocs.io
Project-URL: Repository, https://github.com/patriotresearch/ariadne-extended
Project-URL: Source, https://github.com/patriotresearch/ariadne-extended
